{
  "fortnite king#5068יום שלישי 23 אוקטובר 2018": "Oof",
  "Āľï \"Ł\"#1995יום שלישי 23 אוקטובר 2018": "Oof",
  "Geekid812 | Halloween#9926יום שלישי 23 אוקטובר 2018": "Oof",
  "!AyScorch#8435יום רביעי 24 אוקטובר 2018": "Oof",
  "Dice👻#7725יום רביעי 24 אוקטובר 2018": "Oof",
  "Nik#2820יום רביעי 24 אוקטובר 2018": "Oof",
  "fortnite king#5068יום רביעי 24 אוקטובר 2018": "Oof",
  "Geekid812 | Halloween#9926יום רביעי 24 אוקטובר 2018": "Oof",
  "T0rn#5284יום רביעי 24 אוקטובר 2018": "Oof",
  "ALabre#4726יום רביעי 24 אוקטובר 2018": "Oof",
  "Mehteran#5519יום רביעי 24 אוקטובר 2018": "Oof",
  "𝘾𝘼𝙋𝙎𝙇𝙊𝘾𝙆#5687יום רביעי 24 אוקטובר 2018": "Oof",
  "spσσkч scαrч vαlтυυ#4227יום רביעי 24 אוקטובר 2018": "Oof",
  "unicornkid#8997יום רביעי 24 אוקטובר 2018": "Oof",
  "Nik#2820יום חמישי 25 אוקטובר 2018": "Oof",
  "Āľï \"Ł\"#1995יום חמישי 25 אוקטובר 2018": "Oof",
  "Dice👻#7725יום חמישי 25 אוקטובר 2018": "Oof",
  "antimemerepelant#0618יום חמישי 25 אוקטובר 2018": "Oof",
  "chckN#3931יום חמישי 25 אוקטובר 2018": "Oof",
  "Tytgamer#1573יום חמישי 25 אוקטובר 2018": "Oof",
  "unicornkid#8997יום חמישי 25 אוקטובר 2018": "Oof",
  "ALabre#4726יום חמישי 25 אוקטובר 2018": "Oof",
  "Mehteran#5519יום חמישי 25 אוקטובר 2018": "Oof",
  "aesthetic lil boi#5977יום חמישי 25 אוקטובר 2018": "Oof",
  "tik tok#2432יום חמישי 25 אוקטובר 2018": "Oof",
  "Potato Chips#7711יום חמישי 25 אוקטובר 2018": "Oof",
  "hi me kill tower#6383יום שישי 26 אוקטובר 2018": "Oof",
  "Āľï \"Ł\"#1995יום שישי 26 אוקטובר 2018": "Oof",
  "Dice👻#7725יום שישי 26 אוקטובר 2018": "Oof",
  "MonKid#1244יום שישי 26 אוקטובר 2018": "Oof",
  "Polar#0634יום שישי 26 אוקטובר 2018": "Oof",
  "T0rn#5284יום שישי 26 אוקטובר 2018": "Oof",
  "Spooky Spirit Goodna 💞#2087יום שישי 26 אוקטובר 2018": "Oof",
  "ALabre#4726יום שישי 26 אוקטובר 2018": "Oof",
  "Binkie01#6183יום שישי 26 אוקטובר 2018": "Oof",
  "una#5628יום שישי 26 אוקטובר 2018": "Oof",
  "KingDaily (DEATH)#5899יום שישי 26 אוקטובר 2018": "Oof",
  "hi me kill tower#6383שבת 27 אוקטובר 2018": "Oof",
  "Āľï \"Ł\"#1995שבת 27 אוקטובר 2018": "Oof",
  "Dice👻#7725שבת 27 אוקטובר 2018": "Oof",
  "Mehteran#5519שבת 27 אוקטובר 2018": "Oof",
  "Binkie01#6183שבת 27 אוקטובר 2018": "Oof",
  "KLA|kjkszpj11111#2201שבת 27 אוקטובר 2018": "Oof",
  "Tytgamer#1573שבת 27 אוקטובר 2018": "Oof",
  "fortnite king#5068שבת 27 אוקטובר 2018": "Oof",
  "DA NEKO ATTACKKKK!#9620שבת 27 אוקטובר 2018": "Oof",
  "~ECNAHC TSAL~#6383שבת 27 אוקטובר 2018": "Oof",
  "RavenclawsEagle#1546שבת 27 אוקטובר 2018": "Oof",
  "Nalani1619#7628שבת 27 אוקטובר 2018": "Oof",
  "👑Amaçsız Kemal👑#2201שבת 27 אוקטובר 2018": "Oof",
  "Dice.exe#7725שבת 27 אוקטובר 2018": "Oof",
  "!AyScorch#8435יום ראשון 28 אוקטובר 2018": "Oof",
  "Dice.exe#7725יום ראשון 28 אוקטובר 2018": "Oof",
  "fortnite king#5068יום ראשון 28 אוקטובר 2018": "Oof",
  "Āľï \"Ł\"#1995יום ראשון 28 אוקטובר 2018": "Oof",
  "Tytgamer#1573יום ראשון 28 אוקטובר 2018": "Oof",
  "una#5628יום ראשון 28 אוקטובר 2018": "Oof",
  "RavenclawsEagle#1546יום ראשון 28 אוקטובר 2018": "Oof",
  "~ECNAHC TSAL~#6383יום ראשון 28 אוקטובר 2018": "Oof",
  "Geekid812 | Halloween#9926יום ראשון 28 אוקטובר 2018": "Oof",
  "ALabre#4726יום ראשון 28 אוקטובר 2018": "Oof",
  "Dice.exe#7725יום שני 29 אוקטובר 2018": "Oof",
  "Āľï \"Ł\"#1995יום שני 29 אוקטובר 2018": "Oof",
  "~ECNAHC TSAL~#6383יום שלישי 30 אוקטובר 2018": "Oof",
  "fortnite king#5068יום שלישי 30 אוקטובר 2018": "Oof",
  "Agent Potato#7711יום שלישי 30 אוקטובר 2018": "Oof",
  "Tytgamer#1573יום שלישי 30 אוקטובר 2018": "Oof",
  "Geekid812 | Halloween#9926יום שלישי 30 אוקטובר 2018": "Oof",
  "Nalani1619#7628יום שלישי 30 אוקטובר 2018": "Oof",
  "Agent Potato#7711יום רביעי 31 אוקטובר 2018": "Oof",
  "~GNINRAW LANIF~#6383יום רביעי 31 אוקטובר 2018": "Oof",
  "<•[♡]•>#7725יום רביעי 31 אוקטובר 2018": "Oof",
  "Geekid812 | Halloween#9926יום רביעי 31 אוקטובר 2018": "Oof",
  "Āľï \"Ł\"#1995יום רביעי 31 אוקטובר 2018": "Oof",
  "TheOrangeJuice#8426יום רביעי 31 אוקטובר 2018": "Oof",
  "•[D]•[I]•[C]•[E]•#7725יום רביעי 31 אוקטובר 2018": "Oof",
  "Mehteran#5519יום רביעי 31 אוקטובר 2018": "Oof",
  "Petingoso#6208יום רביעי 31 אוקטובר 2018": "Oof",
  "fortnite king#5068יום רביעי 31 אוקטובר 2018": "Oof",
  "TheOrangeJuice#8426יום חמישי 01 נובמבר 2018": "Oof",
  "RavenclawsEagle#1546יום חמישי 01 נובמבר 2018": "Oof",
  "~GNINRAW LANIF~#6383יום חמישי 01 נובמבר 2018": "Oof",
  "fortnite king#5068יום חמישי 01 נובמבר 2018": "Oof",
  "Āľï \"Ł\"#1995יום חמישי 01 נובמבר 2018": "Oof",
  "!AyScorch#8435יום חמישי 01 נובמבר 2018": "Oof",
  "🎃 LOLYOU1337 🎃#9259יום חמישי 01 נובמבר 2018": "Oof",
  "•[D]•[I]•[C]•[E]•#7725יום חמישי 01 נובמבר 2018": "Oof",
  "DA NEKO ATTACKKKK!#9620יום חמישי 01 נובמבר 2018": "Oof",
  "Geekid812 | Halloween#9926יום חמישי 01 נובמבר 2018": "Oof",
  "Petingoso#6208יום חמישי 01 נובמבר 2018": "Oof",
  "( ͡° ͜ʖ ͡°)#3670יום חמישי 01 נובמבר 2018": "Oof",
  "Tytgamer#1573יום חמישי 01 נובמבר 2018": "Oof",
  "RealSsumRealRappa#8072יום חמישי 01 נובמבר 2018": "Oof",
  "NotTapL (DM for Game)#4700יום חמישי 01 נובמבר 2018": "Oof",
  "🔀ERDEM🔀#5562יום חמישי 01 נובמבר 2018": "Oof",
  "Dice#7725יום חמישי 01 נובמבר 2018": "Oof",
  "T0rn#5284יום חמישי 01 נובמבר 2018": "Oof",
  "TheOrangeJuice#8426יום שישי 02 נובמבר 2018": "Oof",
  "( ͡° ͜ʖ ͡°)#3670יום שישי 02 נובמבר 2018": "Oof",
  "fortnite king#5068יום שישי 02 נובמבר 2018": "Oof",
  "🎃 LOLYOU1337 🎃#9259יום שישי 02 נובמבר 2018": "Oof",
  "Dice#7725יום שישי 02 נובמבר 2018": "Oof",
  "Agent Potato#7711יום שישי 02 נובמבר 2018": "Oof",
  "Lakerboy#1353יום שישי 02 נובמבר 2018": "Oof",
  "SebastianSasaki#1552יום שישי 02 נובמבר 2018": "Oof",
  "DT. Connor RK-800#5991יום שישי 02 נובמבר 2018": "Oof",
  "i_reid_books#5942יום שישי 02 נובמבר 2018": "Oof",
  "Geekid812#9926יום שישי 02 נובמבר 2018": "Oof",
  "h4cked Tytgamer#1573יום שישי 02 נובמבר 2018": "Oof",
  "Āľï \"Ł\"#1995יום שישי 02 נובמבר 2018": "Oof",
  "JustCallMeGem#3018יום שישי 02 נובמבר 2018": "Oof",
  "aimi-sama#1370יום שישי 02 נובמבר 2018": "Oof",
  "Death2All#5790יום שישי 02 נובמבר 2018": "Oof",
  "[Off in 2d] Dice#7725יום שישי 02 נובמבר 2018": "Oof",
  "AquaChiBlue#5698יום שישי 02 נובמבר 2018": "Oof",
  "🎃 LOLYOU1337 🎃#9259שבת 03 נובמבר 2018": "Oof",
  "SMOL GHOST#5068שבת 03 נובמבר 2018": "Oof",
  "Dice#7725שבת 03 נובמבר 2018": "Oof",
  "TheMadRanter#9136שבת 03 נובמבר 2018": "Oof",
  "h4cked Tytgamer#1573שבת 03 נובמבר 2018": "Oof",
  "Easy#6862שבת 03 נובמבר 2018": "Oof",
  "Āľï \"Ł\"#1995שבת 03 נובמבר 2018": "Oof",
  "~GNINRAW LANIF~#6383שבת 03 נובמבר 2018": "Oof",
  "Mellowmoonlight#2028שבת 03 נובמבר 2018": "Oof",
  "Fortnite King#5068שבת 03 נובמבר 2018": "Oof",
  "🔀ERDEM🔀#5562שבת 03 נובמבר 2018": "Oof",
  "TheOrangeJuice#8426שבת 03 נובמבר 2018": "Oof",
  "( ͡° ͜ʖ ͡°)#3670שבת 03 נובמבר 2018": "Oof",
  "Agent Potato#7711שבת 03 נובמבר 2018": "Oof",
  "NotTapL (DM for Game)#4700שבת 03 נובמבר 2018": "Oof",
  "Flwr04#1752שבת 03 נובמבר 2018": "Oof",
  "Vizitys#1957שבת 03 נובמבר 2018": "Oof",
  "procreeper1#6729שבת 03 נובמבר 2018": "Oof",
  "RavenclawsEagle#1546שבת 03 נובמבר 2018": "Oof",
  "Mehteran#5519שבת 03 נובמבר 2018": "Oof",
  "🎃 LOLYOU1337 🎃#9259יום ראשון 04 נובמבר 2018": "Oof",
  "TheOrangeJuice#8426יום ראשון 04 נובמבר 2018": "Oof",
  "Fortnite King#5068יום ראשון 04 נובמבר 2018": "Oof",
  "Dice#7725יום ראשון 04 נובמבר 2018": "Oof",
  "h4cked Tytgamer#1573יום ראשון 04 נובמבר 2018": "Oof",
  "Geekid812#9926יום ראשון 04 נובמבר 2018": "Oof",
  "i_reid_books#5942יום ראשון 04 נובמבר 2018": "Oof",
  "~GNINRAW LANIF~#6383יום ראשון 04 נובמבר 2018": "Oof",
  "steve 🇦🇹#3216יום ראשון 04 נובמבר 2018": "Oof",
  "~GNINRAW LANIF~#6383יום שני 05 נובמבר 2018": "Oof",
  "Dice#7725יום שני 05 נובמבר 2018": "Oof",
  "Āľï \"Ł\"#1995יום שני 05 נובמבר 2018": "Oof",
  "Fortnite King#5068יום שני 05 נובמבר 2018": "Oof",
  "Vizitys#1957יום שני 05 נובמבר 2018": "Oof",
  "§ðmñðlêñ†🎃#6314יום שני 05 נובמבר 2018": "Oof",
  "Agent Potato#7711יום שני 05 נובמבר 2018": "Oof",
  "🎃 LOLYOU1337 🎃#9259יום שני 05 נובמבר 2018": "Oof",
  "Loser#0336יום שני 05 נובמבר 2018": "Oof",
  "MathiPira#1414יום שלישי 06 נובמבר 2018": "Oof",
  "TheOrangeJuice#8426יום שלישי 06 נובמבר 2018": "Oof",
  "Dice#7725יום שלישי 06 נובמבר 2018": "Oof",
  "~GNINRAW LANIF~#6383יום שלישי 06 נובמבר 2018": "Oof",
  "Mehteran#5519יום שלישי 06 נובמבר 2018": "Oof",
  "dogwispherer#2557יום שלישי 06 נובמבר 2018": "Oof",
  "Geekid812#9926יום שלישי 06 נובמבר 2018": "Oof",
  "Fortnite King#5068יום שלישי 06 נובמבר 2018": "Oof",
  "( ͡° ͜ʖ ͡°)#3670יום שלישי 06 נובמבר 2018": "Oof",
  "Flwr04#1752יום שלישי 06 נובמבר 2018": "Oof",
  "!AyScorch#8435יום שלישי 06 נובמבר 2018": "Oof",
  "🔀ERDEM🔀#5562יום שלישי 06 נובמבר 2018": "Oof",
  "Agent Potato#7711יום שלישי 06 נובמבר 2018": "Oof",
  "Āľï \"Ł\"#1995יום שלישי 06 נובמבר 2018": "Oof",
  "loomafish#3303יום שלישי 06 נובמבר 2018": "Oof",
  "DT. Connor RK-800#5991יום שלישי 06 נובמבר 2018": "Oof",
  "TheMadRanter#9136יום רביעי 07 נובמבר 2018": "Oof",
  "Āľï \"Ł\"#1995יום רביעי 07 נובמבר 2018": "Oof",
  "Fortnite King#5068יום רביעי 07 נובמבר 2018": "Oof",
  "~GNINRAW LANIF~#6383יום רביעי 07 נובמבר 2018": "Oof",
  "Hironaiku#0321יום רביעי 07 נובמבר 2018": "Oof",
  "Dice#7725יום רביעי 07 נובמבר 2018": "Oof",
  "🔀ERDEM🔀#5562יום רביעי 07 נובמבר 2018": "Oof",
  "DT. Connor RK-800#5991יום רביעי 07 נובמבר 2018": "Oof",
  "TheOrangeJuice#8426יום רביעי 07 נובמבר 2018": "Oof",
  "MisterZ#6763יום רביעי 07 נובמבר 2018": "Oof",
  "RavenclawsEagle#1546יום רביעי 07 נובמבר 2018": "Oof",
  "Geekid812#9926יום רביעי 07 נובמבר 2018": "Oof",
  "Agent Potato#7711יום רביעי 07 נובמבר 2018": "Oof",
  "🎃 LOLYOU1337 🎃#9259יום רביעי 07 נובמבר 2018": "Oof",
  "DA NEKO ATTACKKKK!#9620יום רביעי 07 נובמבר 2018": "Oof",
  "Death2All#5790יום רביעי 07 נובמבר 2018": "Oof",
  "Tytgamer#1573יום רביעי 07 נובמבר 2018": "Oof",
  "Dice#7725יום חמישי 08 נובמבר 2018": "Oof",
  "🔀ERDEM🔀#5562יום חמישי 08 נובמבר 2018": "Oof",
  "DA NEKO ATTACKKKK!#9620יום חמישי 08 נובמבר 2018": "Oof",
  "Tytgamer#1573יום חמישי 08 נובמבר 2018": "Oof",
  "Fortnite King#5068יום חמישי 08 נובמבר 2018": "Oof",
  "wan#2920יום חמישי 08 נובמבר 2018": "Oof",
  "Āľï \"Ł\"#1995יום חמישי 08 נובמבר 2018": "Oof",
  "Geekid812#9926יום חמישי 08 נובמבר 2018": "Oof",
  "TheOrangeJuice#8426יום שישי 09 נובמבר 2018": "Oof",
  "Āľï \"Ł\"#1995יום שישי 09 נובמבר 2018": "Oof",
  "~GNINRAW LANIF~#6383יום שישי 09 נובמבר 2018": "Oof",
  "Dice#7725יום שישי 09 נובמבר 2018": "Oof",
  "DA NEKO ATTACKKKK!#9620יום שישי 09 נובמבר 2018": "Oof",
  "Fortnite King#5068יום שישי 09 נובמבר 2018": "Oof",
  "wan#2920יום שישי 09 נובמבר 2018": "Oof",
  "Hironaiku#0321יום שישי 09 נובמבר 2018": "Oof",
  "piemel [ping for help]#7395יום שישי 09 נובמבר 2018": "Oof",
  "Geekid812#9926יום שישי 09 נובמבר 2018": "Oof",
  "~GNINRAW LANIF~#6383שבת 10 נובמבר 2018": "Oof",
  "Fortnite King#5068שבת 10 נובמבר 2018": "Oof",
  "Dice#7725שבת 10 נובמבר 2018": "Oof",
  "TheOrangeJuice#8426שבת 10 נובמבר 2018": "Oof",
  "Mehteran#5519שבת 10 נובמבר 2018": "Oof",
  "spoopy tyler#3391שבת 10 נובמבר 2018": "Oof",
  "Geekid812#9926שבת 10 נובמבר 2018": "Oof",
  "Āľï \"Ł\"#1995שבת 10 נובמבר 2018": "Oof",
  "Vizitys#1957שבת 10 נובמבר 2018": "Oof",
  "wan#2920שבת 10 נובמבר 2018": "Oof",
  "Flwr04#1752שבת 10 נובמבר 2018": "Oof",
  "Milky#9999שבת 10 נובמבר 2018": "Oof",
  "🔀ERDEM🔀#5562שבת 10 נובמבר 2018": "Oof",
  "Ravenclawseagle#1546שבת 10 נובמבר 2018": "Oof",
  "Āľï \"Ł\"#1995יום ראשון 11 נובמבר 2018": "Oof",
  "Dice#7725יום ראשון 11 נובמבר 2018": "Oof",
  "Fortnite King#5068יום ראשון 11 נובמבר 2018": "Oof",
  "🔀ERDEM🔀#5562יום ראשון 11 נובמבר 2018": "Oof",
  "I am not here, I did not exist#0201יום ראשון 11 נובמבר 2018": "Oof",
  "TheOrangeJuice#8426יום ראשון 11 נובמבר 2018": "Oof",
  "Mellowmoonlight#2028יום ראשון 11 נובמבר 2018": "Oof",
  "wan#2920יום ראשון 11 נובמבר 2018": "Oof",
  "DT. Connor RK-800#5991יום ראשון 11 נובמבר 2018": "Oof",
  "YIHANG1024#7890יום ראשון 11 נובמבר 2018": "Oof",
  "~GNINRAW LANIF~#6383יום ראשון 11 נובמבר 2018": "Oof",
  "Flwr04#1752יום ראשון 11 נובמבר 2018": "Oof",
  "Mehteran#5519יום ראשון 11 נובמבר 2018": "Oof",
  "Marilina🌻#6575יום ראשון 11 נובמבר 2018": "Oof",
  "ScRiptED#1445יום ראשון 11 נובמבר 2018": "Oof",
  "giulgu17#8174יום ראשון 11 נובמבר 2018": "Oof",
  "Geekid812#9926יום ראשון 11 נובמבר 2018": "Oof",
  "Fortnite King#5068יום שני 12 נובמבר 2018": "Oof",
  "Dice#7725יום שני 12 נובמבר 2018": "Oof",
  "Āľï \"Ł\"#1995יום שני 12 נובמבר 2018": "Oof"
}